pynrds.py
pynrds-0.0.2.dist-info/METADATA
pynrds-0.0.2.dist-info/WHEEL
pynrds-0.0.2.dist-info/entry_points.txt
pynrds-0.0.2.dist-info/top_level.txt
pynrds-0.0.2.dist-info/RECORD
