Metadata-Version: 2.1
Name: pynrds
Version: 0.0.2
Summary: A Complete Python Wrapper for the NAR NRDS API Service
Home-page: https://github.com/mansard/pynrds
Author: Jeremey Bingham
Author-email: info@mansard.net
License: UNKNOWN
Platform: UNKNOWN
Classifier: Programming Language :: Python :: 3.7
Classifier: Operating System :: OS Independent
Classifier: Development Status :: 1 - Planning
Requires-Python: >=3.7
Requires-Dist: requests
Requires-Dist: pandas
Requires-Dist: numpy
Requires-Dist: mimesis
Requires-Dist: faker
Requires-Dist: delorean
